setup.py
atodorov_test/__init__.py
atodorov_test.egg-info/PKG-INFO
atodorov_test.egg-info/SOURCES.txt
atodorov_test.egg-info/dependency_links.txt
atodorov_test.egg-info/top_level.txt