Metadata-Version: 1.0
Name: atodorov-test
Version: 0.3.4
Summary: Dummy test package, please ignore.
Home-page: https://github.com/atodorov/bztest
Author: Alexander Todorov
Author-email: atodorov@nopam.otb.bg
License: BSD
Platform: UNKNOWN
